<?xml version='1.0'?><Mission><MissionNumber></MissionNumber><OriginalMissionNumber></OriginalMissionNumber><Unit>ET 1/61</Unit><Aircraft>FRBAE-MSN12</Aircraft><OriginalAircraft>FRBAE-MSN12</OriginalAircraft><Leg><CallSign>CTM 2057</CallSign><OriginalCallSign>CTM 2057</OriginalCallSign><Be></Be><OriginalBe></OriginalBe><Na></Na><OriginalNa></OriginalNa><ETD>3/12/2015 07:00</ETD><OriginalETD>3/12/2015 07:00</OriginalETD><DepartureAirport>LFOJ</DepartureAirport><OriginalDepartureAirport>LFOJ</OriginalDepartureAirport><ETA>3/12/2015 08:40</ETA><OriginalETA>3/12/2015 08:40</OriginalETA><ArrivalAirport>LFKS</ArrivalAirport><OriginalArrivalAirport>LFKS</OriginalArrivalAirport><CrewMember><Name>CNE PINEAU</Name><Function>CDB</Function><Controle></Controle></CrewMember><CrewMember><Name> KUHLMANN</Name><Function>PIL</Function><Controle></Controle></CrewMember><CrewMember><Name>CNE BORRIEN</Name><Function>PIL</Function><Controle></Controle></CrewMember><CrewMember><Name>ADC COLLIN</Name><Function>MES</Function><Controle></Controle></CrewMember><CrewMember><Name>SGT LAURENT</Name><Function>MES</Function><Controle>CTL</Controle></CrewMember><CrewMember><Name>CCH SOUTILLE</Name><Function>ASO</Function><Controle></Controle></CrewMember><CrewMember><Name> VENARD</Name><Function>EMES</Function><Controle></Controle></CrewMember><CrewMember><Name>LCL ZAMBERY</Name><Function>CE</Function><Controle></Controle></CrewMember><CrewMember><Name>MAJ BOURGUIGNON</Name><Function>CE</Function><Controle>CTR</Controle></CrewMember><CrewMember><Name>SGC HERVE</Name><Function>CE</Function><Controle></Controle></CrewMember><CrewMember><Name>SGC NIATEL</Name><Function>CE</Function><Controle></Controle></CrewMember><CrewMember><Name>CNE DURAZ</Name><Function>CE</Function><Controle></Controle></CrewMember></Leg><Leg><CallSign>CTM 2057</CallSign><OriginalCallSign>CTM 2057</OriginalCallSign><Be></Be><OriginalBe></OriginalBe><Na></Na><OriginalNa></OriginalNa><ETD>3/12/2015 9:40</ETD><OriginalETD>3/12/2015 9:40</OriginalETD><DepartureAirport>LFKS</DepartureAirport><OriginalDepartureAirport>LFKS</OriginalDepartureAirport><ETA>3/12/2015 16:25</ETA><OriginalETA>3/12/2015 16:25</OriginalETA><ArrivalAirport>HDAM</ArrivalAirport><OriginalArrivalAirport>HDAM</OriginalArrivalAirport><CrewMember><Name>CNE PINEAU</Name><Function>CDB</Function><Controle></Controle></CrewMember><CrewMember><Name> KUHLMANN</Name><Function>PIL</Function><Controle></Controle></CrewMember><CrewMember><Name>CNE BORRIEN</Name><Function>PIL</Function><Controle></Controle></CrewMember><CrewMember><Name>ADC COLLIN</Name><Function>MES</Function><Controle></Controle></CrewMember><CrewMember><Name>SGT LAURENT</Name><Function>MES</Function><Controle>CTL</Controle></CrewMember><CrewMember><Name>CCH SOUTILLE</Name><Function>ASO</Function><Controle></Controle></CrewMember><CrewMember><Name> VENARD</Name><Function>EMES</Function><Controle></Controle></CrewMember><CrewMember><Name>LCL ZAMBERY</Name><Function>CE</Function><Controle></Controle></CrewMember><CrewMember><Name>MAJ BOURGUIGNON</Name><Function>CE</Function><Controle>CTR</Controle></CrewMember><CrewMember><Name>SGC HERVE</Name><Function>CE</Function><Controle></Controle></CrewMember><CrewMember><Name>SGC NIATEL</Name><Function>CE</Function><Controle></Controle></CrewMember><CrewMember><Name>CNE DURAZ</Name><Function>CE</Function><Controle></Controle></CrewMember></Leg><Leg><CallSign>CTM 2057</CallSign><OriginalCallSign>CTM 2057</OriginalCallSign><Be></Be><OriginalBe></OriginalBe><Na></Na><OriginalNa></OriginalNa><ETD>4/12/2015 09:00</ETD><OriginalETD>4/12/2015 09:00</OriginalETD><DepartureAirport>HDAM</DepartureAirport><OriginalDepartureAirport>HDAM</OriginalDepartureAirport><ETA>4/12/2015 13:20</ETA><OriginalETA>4/12/2015 13:20</OriginalETA><ArrivalAirport>OTBD</ArrivalAirport><OriginalArrivalAirport>OTBD</OriginalArrivalAirport><CrewMember><Name>CNE PINEAU</Name><Function>CDB</Function><Controle></Controle></CrewMember><CrewMember><Name> KUHLMANN</Name><Function>PIL</Function><Controle></Controle></CrewMember><CrewMember><Name>CNE BORRIEN</Name><Function>PIL</Function><Controle></Controle></CrewMember><CrewMember><Name>ADC COLLIN</Name><Function>MES</Function><Controle></Controle></CrewMember><CrewMember><Name>SGT LAURENT</Name><Function>MES</Function><Controle>CTL</Controle></CrewMember><CrewMember><Name>CCH SOUTILLE</Name><Function>ASO</Function><Controle></Controle></CrewMember><CrewMember><Name> VENARD</Name><Function>EMES</Function><Controle></Controle></CrewMember><CrewMember><Name>LCL ZAMBERY</Name><Function>CE</Function><Controle></Controle></CrewMember><CrewMember><Name>MAJ BOURGUIGNON</Name><Function>CE</Function><Controle>CTR</Controle></CrewMember><CrewMember><Name>SGC HERVE</Name><Function>CE</Function><Controle></Controle></CrewMember><CrewMember><Name>SGC NIATEL</Name><Function>CE</Function><Controle></Controle></CrewMember><CrewMember><Name>EAM DTI</Name><Function>CE</Function><Controle></Controle></CrewMember><CrewMember><Name>EAM DTI</Name><Function>CE</Function><Controle></Controle></CrewMember></Leg><Leg><CallSign>CTM 2057</CallSign><OriginalCallSign>CTM 2057</OriginalCallSign><Be></Be><OriginalBe></OriginalBe><Na></Na><OriginalNa></OriginalNa><ETD>4/12/2015 15:20</ETD><OriginalETD>4/12/2015 15:20</OriginalETD><DepartureAirport>OTBD</DepartureAirport><OriginalDepartureAirport>OTBD</OriginalDepartureAirport><ETA>4/12/2015 19:25</ETA><OriginalETA>4/12/2015 19:25</OriginalETA><ArrivalAirport>HDAM</ArrivalAirport><OriginalArrivalAirport>HDAM</OriginalArrivalAirport><CrewMember><Name>CNE PINEAU</Name><Function>CDB</Function><Controle></Controle></CrewMember><CrewMember><Name> KUHLMANN</Name><Function>PIL</Function><Controle></Controle></CrewMember><CrewMember><Name>CNE BORRIEN</Name><Function>PIL</Function><Controle></Controle></CrewMember><CrewMember><Name>ADC COLLIN</Name><Function>MES</Function><Controle></Controle></CrewMember><CrewMember><Name>SGT LAURENT</Name><Function>MES</Function><Controle>CTL</Controle></CrewMember><CrewMember><Name>CCH SOUTILLE</Name><Function>ASO</Function><Controle></Controle></CrewMember><CrewMember><Name> VENARD</Name><Function>EMES</Function><Controle></Controle></CrewMember><CrewMember><Name>LCL ZAMBERY</Name><Function>CE</Function><Controle></Controle></CrewMember><CrewMember><Name>MAJ BOURGUIGNON</Name><Function>CE</Function><Controle>CTR</Controle></CrewMember><CrewMember><Name>SGC HERVE</Name><Function>CE</Function><Controle></Controle></CrewMember><CrewMember><Name>SGC NIATEL</Name><Function>CE</Function><Controle></Controle></CrewMember><CrewMember><Name>EAM DTI</Name><Function>CE</Function><Controle></Controle></CrewMember><CrewMember><Name>EAM DTI</Name><Function>CE</Function><Controle></Controle></CrewMember></Leg></Mission>